<?xml version="1.0" encoding="UTF-8"?>
<objects serializationModel="Studio.02.03.00">
	<object class="AudioFile" id="{778b11b8-15e4-44c2-a9d1-f83ba7c388ca}">
		<property name="assetPath">
			<value>dog-walking-3.wav</value>
		</property>
		<property name="frequencyInKHz">
			<value>44.0999985</value>
		</property>
		<property name="channelCount">
			<value>2</value>
		</property>
		<property name="length">
			<value>0.27043083900226755</value>
		</property>
		<relationship name="masterAssetFolder">
			<destination>{33e68a6b-ad22-4898-887f-aef67ec1c75f}</destination>
		</relationship>
	</object>
</objects>
